{
  "backend": "postgres",
  "batch_size": 10,
  "dataset_name": "jobs_1k.jsonl",
  "dataset_sha256": null,
  "db_write_ms_p50": 0.0,
  "db_write_ms_p95": 1.0,
  "duplicate_attempts": 0,
  "duration_seconds": 1.855888,
  "experiment_id": "exp009_retry_storm",
  "failed_attempts": 108,
  "finished_at": "2026-05-20T15:20:38.171240+00:00",
  "job_count_target": 1000,
  "jobs_per_second": 538.8256187873407,
  "max_dead_depth": 0,
  "max_in_flight_depth": 36,
  "max_ready_depth": 1000,
  "processing_ms_p50": 0.0,
  "processing_ms_p95": 1.0,
  "run_id": "v02-retry-postgres-rate005",
  "started_at": "2026-05-20T15:20:36.315352+00:00",
  "successful_attempts": 1000,
  "total_attempts": 1108,
  "unique_attempted_jobs": 1000,
  "unique_processed_jobs": 1000,
  "worker_count": 4
}
